aws_sso_lib/__init__.py
aws_sso_lib/assignments.py
aws_sso_lib/browser.py
aws_sso_lib/compat.py
aws_sso_lib/config.py
aws_sso_lib/config_file_writer.py
aws_sso_lib/exceptions.py
aws_sso_lib/fake_identifiers.py
aws_sso_lib/format.py
aws_sso_lib/lookup.py
aws_sso_lib/sso.py
aws_sso_lib/vendored_botocore/__init__.py
aws_sso_lib/vendored_botocore/exceptions.py
aws_sso_lib/vendored_botocore/utils.py
aws_sso_lib-1.14.0.dist-info/WHEEL
aws_sso_lib-1.14.0.dist-info/METADATA
aws_sso_lib-1.14.0.dist-info/RECORD
