Metadata-Version: 2.1
Name: aws-sso-lib
Version: 1.14.0
Summary: Library to make AWS SSO easier
Home-page: https://github.com/benkehoe/aws-sso-util/blob/master/lib/README.md
License: Apache-2.0
Author: Ben Kehoe
Author-email: ben@kehoe.io
Requires-Python: >=3.7,<4.0
Classifier: Development Status :: 4 - Beta
Classifier: Intended Audience :: Developers
Classifier: Intended Audience :: System Administrators
Classifier: License :: OSI Approved :: Apache Software License
Classifier: Operating System :: OS Independent
Classifier: Programming Language :: Python :: 3
Classifier: Programming Language :: Python :: 3.7
Classifier: Programming Language :: Python :: 3.8
Classifier: Programming Language :: Python :: 3.9
Classifier: Programming Language :: Python :: 3.10
Classifier: Programming Language :: Python :: 3.11
Classifier: Topic :: Software Development :: Libraries
Classifier: Topic :: Utilities
Requires-Dist: aws-error-utils (>=2.4,<3.0)
Requires-Dist: boto3 (>=1.24.60,<2.0.0)
Project-URL: Repository, https://github.com/benkehoe/aws-sso-util
